promptlyzer/__init__.py
promptlyzer/billing.py
promptlyzer/client.py
promptlyzer/deployments.py
promptlyzer/exceptions.py
promptlyzer/prompt_manager.py
promptlyzer/utils.py
promptlyzer/inference/__init__.py
promptlyzer/inference/anthropic_provider.py
promptlyzer/inference/base.py
promptlyzer/inference/manager.py
promptlyzer/inference/openai_provider.py
promptlyzer/inference/together_provider.py
promptlyzer-1.5.1.dist-info/LICENCE
promptlyzer-1.5.1.dist-info/METADATA
promptlyzer-1.5.1.dist-info/WHEEL
promptlyzer-1.5.1.dist-info/top_level.txt
promptlyzer-1.5.1.dist-info/RECORD
