Metadata-Version: 2.1
Name: promptlyzer
Version: 1.5.1
Summary: Official Python SDK for Promptlyzer - Multi-model routing layer for LLMs
Home-page: https://promptlyzer.com
Author: Promptlyzer
Author-email: contact@promptlyzer.com
License: UNKNOWN
Project-URL: Homepage, https://promptlyzer.com
Platform: UNKNOWN
Classifier: Development Status :: 4 - Beta
Classifier: Intended Audience :: Developers
Classifier: License :: OSI Approved :: MIT License
Classifier: Programming Language :: Python :: 3
Classifier: Programming Language :: Python :: 3.7
Classifier: Programming Language :: Python :: 3.8
Classifier: Programming Language :: Python :: 3.9
Classifier: Programming Language :: Python :: 3.10
Classifier: Programming Language :: Python :: 3.11
Classifier: Programming Language :: Python :: 3.12
Requires-Python: >=3.7
License-File: LICENCE
Requires-Dist: requests (>=2.31.0)
Requires-Dist: aiohttp (>=3.9.0)
Requires-Dist: openai (>=1.0.0)
Requires-Dist: anthropic (>=0.15.0)
Requires-Dist: nest-asyncio (>=1.5.6)
